json2toon/__init__.py
json2toon/cli.py
json2toon/decoder.py
json2toon/encoder.py
json2toon/py.typed
json2toon-0.1.2.dist-info/WHEEL
json2toon-0.1.2.dist-info/entry_points.txt
json2toon-0.1.2.dist-info/METADATA
json2toon-0.1.2.dist-info/RECORD
