Metadata-Version: 2.3
Name: json2toon
Version: 0.1.2
Summary: Bidirectional converter between JSON and TOON (Token-Oriented Object Notation) format with full spec support
Keywords: json,toon,converter,serialization,llm,token-optimization
Author: Maqbool Thoufeeq Tharayil
Author-email: Maqbool Thoufeeq Tharayil <maqboolthoufeeq@gmail.com>
License: MIT
Classifier: Development Status :: 3 - Alpha
Classifier: Intended Audience :: Developers
Classifier: License :: OSI Approved :: MIT License
Classifier: Programming Language :: Python :: 3
Classifier: Programming Language :: Python :: 3.12
Classifier: Programming Language :: Python :: 3.13
Classifier: Topic :: Software Development :: Libraries :: Python Modules
Classifier: Topic :: Text Processing
Classifier: Topic :: Utilities
Requires-Dist: pytest>=8.0.0 ; extra == 'dev'
Requires-Dist: pytest-cov>=4.1.0 ; extra == 'dev'
Requires-Dist: mypy>=1.8.0 ; extra == 'dev'
Requires-Dist: ruff>=0.6.0 ; extra == 'dev'
Requires-Python: >=3.12
Project-URL: Documentation, https://github.com/maqboolthoufeeq/json2toon#readme
Project-URL: Homepage, https://github.com/maqboolthoufeeq/json2toon/
Project-URL: Issues, https://github.com/maqboolthoufeeq/json2toon/issues
Project-URL: Repository, https://github.com/maqboolthoufeeq/json2toon/
Provides-Extra: dev
